sparclur/__init__.py
sparclur/_astrotruther.py
sparclur/_detect_chaos.py
sparclur/_floodlight.py
sparclur/_font_extractor.py
sparclur/_hybrid.py
sparclur/_image_data_extractor.py
sparclur/_metaclass.py
sparclur/_metadata_extractor.py
sparclur/_parser.py
sparclur/_pdf_reports.py
sparclur/_prc_sim.py
sparclur/_reforge.py
sparclur/_renderer.py
sparclur/_roll_back.py
sparclur/_spotlight.py
sparclur/_text_compare.py
sparclur/_text_extractor.py
sparclur/_tracer.py
sparclur/lit_sparclur/__init__.py
sparclur/lit_sparclur/_lit_font.py
sparclur/lit_sparclur/_lit_helper.py
sparclur/lit_sparclur/_lit_meta.py
sparclur/lit_sparclur/_lit_prc.py
sparclur/lit_sparclur/_lit_ptc.py
sparclur/lit_sparclur/_lit_pxc.py
sparclur/lit_sparclur/_lit_raw.py
sparclur/lit_sparclur/_non_parser.py
sparclur/lit_sparclur/lit_sparclur.py
sparclur/parsers/__init__.py
sparclur/parsers/_arlington.py
sparclur/parsers/_ghostscript.py
sparclur/parsers/_mupdf.py
sparclur/parsers/_pdfcpu.py
sparclur/parsers/_pdfium.py
sparclur/parsers/_pdfminer.py
sparclur/parsers/_poppler.py
sparclur/parsers/_poppler_helpers.py
sparclur/parsers/_qpdf.py
sparclur/parsers/_xpdf.py
sparclur/parsers/present_parsers.py
sparclur/prc/__init__.py
sparclur/prc/_analyze.py
sparclur/prc/_prc.py
sparclur/prc/_viz.py
sparclur/trawler/__init__.py
sparclur/trawler/_highlight.py
sparclur/utils/__init__.py
sparclur/utils/_config.py
sparclur/utils/_tools.py
sparclur-2022.5.3.data/data/etc/sparclur/sparclur.yaml
sparclur-2022.5.3.data/data/etc/sparclur/resources/AH20210114-modified.pdf
sparclur-2022.5.3.data/data/etc/sparclur/resources/hello_world_hand_edit.pdf
sparclur-2022.5.3.data/data/etc/sparclur/resources/min_vi.pdf
test/__init__.py
test/parser_tests.py
test/test_arlington.py
test/test_ghostscript.py
test/test_mupdf.py
test/test_pdfcpu.py
test/test_pdfium.py
test/test_pdfminer.py
test/test_poppler.py
test/test_qpdf.py
test/test_xpdf.py
sparclur-2022.5.3.dist-info/LICENSE
sparclur-2022.5.3.dist-info/METADATA
sparclur-2022.5.3.dist-info/WHEEL
sparclur-2022.5.3.dist-info/top_level.txt
sparclur-2022.5.3.dist-info/RECORD
