Metadata-Version: 2.1
Name: sparclur
Version: 2022.5.3
Summary: Tools for analyzing PDF files and comparing PDF parsers
Home-page: https://github.com/levelupresearch/sparclur
Author: Shawn Davis
Author-email: shawn@levelupresearch.com
License: Apache-2.0
Platform: UNKNOWN
Requires-Python: >=3.8
License-File: LICENSE
Requires-Dist: pandas
Requires-Dist: func-timeout
Requires-Dist: numpy
Requires-Dist: scikit-image
Requires-Dist: scikit-learn
Requires-Dist: Pebble
Requires-Dist: tqdm
Requires-Dist: PyMuPDF
Requires-Dist: Pillow
Requires-Dist: matplotlib
Requires-Dist: pytesseract
Requires-Dist: spacy
Requires-Dist: dill
Requires-Dist: pdfminer.six
Requires-Dist: pypdfium2
Requires-Dist: opencv-python
Requires-Dist: ImageHash
Requires-Dist: PyYAML
Requires-Dist: mmh3
Requires-Dist: seaborn
Requires-Dist: plotly
Requires-Dist: docstring-inheritance
